opagen/__init__.py
opagen/main.py
opagen/words.txt
opagen-0.1.2.dist-info/METADATA
opagen-0.1.2.dist-info/WHEEL
opagen-0.1.2.dist-info/entry_points.txt
opagen-0.1.2.dist-info/RECORD
