Metadata-Version: 2.1
Name: opagen
Version: 0.1.2
Summary: generate opa accounts
Author: sweatrs
Requires-Python: >=3.12,<4.0
Classifier: Programming Language :: Python :: 3
Classifier: Programming Language :: Python :: 3.12
Requires-Dist: rich (>=13.7.1,<14.0.0)
Requires-Dist: selenium (>=4.22.0,<5.0.0)
Requires-Dist: setuptools (>=70.2.0,<71.0.0)
Requires-Dist: typer (>=0.12.3,<0.13.0)
Requires-Dist: undetected-chromedriver (>=3.5.5,<4.0.0)
